mopidy_mowecl-0.6.1.data/data/mopidy_mowecl/static/assets/index-CAmS7QKI.css
mopidy_mowecl-0.6.1.data/data/mopidy_mowecl/static/assets/index-CFr_N5U_.js
mopidy_mowecl-0.6.1.data/data/mopidy_mowecl/static/assets/roboto-latin-100-B3mHgoOJ.woff
mopidy_mowecl-0.6.1.data/data/mopidy_mowecl/static/assets/roboto-latin-100-BJNx9A77.woff2
mopidy_mowecl-0.6.1.data/data/mopidy_mowecl/static/assets/roboto-latin-100italic-Bjs4D596.woff
mopidy_mowecl-0.6.1.data/data/mopidy_mowecl/static/assets/roboto-latin-100italic-DkGpOhj0.woff2
mopidy_mowecl-0.6.1.data/data/mopidy_mowecl/static/assets/roboto-latin-300-Cx9SeV6m.woff
mopidy_mowecl-0.6.1.data/data/mopidy_mowecl/static/assets/roboto-latin-300-EvKWBL9d.woff2
mopidy_mowecl-0.6.1.data/data/mopidy_mowecl/static/assets/roboto-latin-300italic-CYatNKLh.woff2
mopidy_mowecl-0.6.1.data/data/mopidy_mowecl/static/assets/roboto-latin-300italic-Uxw9HR3T.woff
mopidy_mowecl-0.6.1.data/data/mopidy_mowecl/static/assets/roboto-latin-400-CEEi-WbQ.woff2
mopidy_mowecl-0.6.1.data/data/mopidy_mowecl/static/assets/roboto-latin-400-CKhRtUFO.woff
mopidy_mowecl-0.6.1.data/data/mopidy_mowecl/static/assets/roboto-latin-400italic-B7WW6HdJ.woff
mopidy_mowecl-0.6.1.data/data/mopidy_mowecl/static/assets/roboto-latin-400italic-DRWWNyaf.woff2
mopidy_mowecl-0.6.1.data/data/mopidy_mowecl/static/assets/roboto-latin-500-BU-otfqs.woff
mopidy_mowecl-0.6.1.data/data/mopidy_mowecl/static/assets/roboto-latin-500-DRg8azjQ.woff2
mopidy_mowecl-0.6.1.data/data/mopidy_mowecl/static/assets/roboto-latin-500italic-CAWXcheQ.woff2
mopidy_mowecl-0.6.1.data/data/mopidy_mowecl/static/assets/roboto-latin-500italic-DC3lxgcN.woff
mopidy_mowecl-0.6.1.data/data/mopidy_mowecl/static/assets/roboto-latin-700-CCwTn0--.woff
mopidy_mowecl-0.6.1.data/data/mopidy_mowecl/static/assets/roboto-latin-700-CqGedB_1.woff2
mopidy_mowecl-0.6.1.data/data/mopidy_mowecl/static/assets/roboto-latin-700italic-C5p_YAqY.woff2
mopidy_mowecl-0.6.1.dist-info/METADATA
mopidy_mowecl-0.6.1.dist-info/WHEEL
mopidy_mowecl-0.6.1.dist-info/entry_points.txt
mopidy_mowecl-0.6.1.dist-info/licenses/LICENSE
mopidy_mowecl-0.6.1.dist-info/RECORD
