Metadata-Version: 2.1
Name: Mopidy-Mowecl
Version: 0.6.1
Summary: Web client for Mopidy
Author-Email: Mathias Millet <mathias@mmill.eu>
License: Apache-2.0
Classifier: Environment :: No Input/Output (Daemon)
Classifier: Intended Audience :: End Users/Desktop
Classifier: License :: OSI Approved :: Apache Software License
Classifier: Operating System :: OS Independent
Classifier: Topic :: Multimedia :: Sound/Audio :: Players
Project-URL: Homepage, https://github.com/sapristi/mopidy-mowecl
Requires-Python: >=3.9
Requires-Dist: Mopidy>=3.0
Requires-Dist: Mopidy-Bookmarks>=0.1.4
Requires-Dist: Pykka>=2.0.1
Requires-Dist: musicbrainzngs>=0.7.1
Provides-Extra: lint
Requires-Dist: black; extra == "lint"
Requires-Dist: check-manifest; extra == "lint"
Requires-Dist: flake8; extra == "lint"
Requires-Dist: flake8-bugbear; extra == "lint"
Requires-Dist: flake8-import-order; extra == "lint"
Requires-Dist: isort[pyproject]; extra == "lint"
Provides-Extra: release
Requires-Dist: twine; extra == "release"
Requires-Dist: wheel; extra == "release"
Provides-Extra: test
Requires-Dist: pytest; extra == "test"
Requires-Dist: pytest-cov; extra == "test"
Provides-Extra: dev
Requires-Dist: black; extra == "dev"
Requires-Dist: check-manifest; extra == "dev"
Requires-Dist: flake8; extra == "dev"
Requires-Dist: flake8-bugbear; extra == "dev"
Requires-Dist: flake8-import-order; extra == "dev"
Requires-Dist: isort[pyproject]; extra == "dev"
Requires-Dist: pytest; extra == "dev"
Requires-Dist: pytest-cov; extra == "dev"
Requires-Dist: twine; extra == "dev"
Requires-Dist: wheel; extra == "dev"
Requires-Dist: setuptools>=75.8.0; extra == "dev"
Requires-Dist: pre-commit>=4.1.0; extra == "dev"
